{
  "s1": {
    "rules": [
      {
        "port": 1,
        "host": "h1",
        "action": "MyIngress.ipv4_forward",
        "table": "MyIngress.ipv4_lpm"
      },
      {
        "port": 3,
        "host": "h2",
        "action": "MyIngress.ipv4_forward",
        "table": "MyIngress.ipv4_lpm"
      }
    ],
    "program": "simple",
    "digest": ""
  },
  "s2": {
    "rules": [],
    "program": "simple",
    "digest": ""
  },
  "s3": {
    "rules": [
      {
        "port": 1,
        "host": "h1",
        "action": "MyIngress.ipv4_forward",
        "table": "MyIngress.ipv4_lpm1"
      },
      {
        "port": 2,
        "host": "h2",
        "action": "MyIngress.ipv4_forward",
        "table": "MyIngress.ipv4_lpm1"
      }
    ],
    "program": "simple1",
    "digest": ""
  },
  "s4": {
    "rules": [
      {
        "port": 1,
        "host": "h2",
        "action": "MyIngress.ipv4_forward",
        "table": "MyIngress.ipv4_lpm1"
      },
      {
        "port": 3,
        "host": "h1",
        "action": "MyIngress.ipv4_forward",
        "table": "MyIngress.ipv4_lpm1"
      }
    ],
    "program": "simple1",
    "digest": ""
  }
}